tfdocs/__init__.py
tfdocs/__main__.py
tfdocs/cli.py
tfdocs/readme.py
tfdocs/utils.py
tfdocs/version.py
tfdocs-1.3.dist-info/METADATA
tfdocs-1.3.dist-info/WHEEL
tfdocs-1.3.dist-info/entry_points.txt
tfdocs-1.3.dist-info/licenses/LICENCE
tfdocs-1.3.dist-info/RECORD
