Metadata-Version: 2.4
Name: tfdocs
Version: 1.3
Summary: Documentation generator for Terraform modules
Project-URL: Homepage, https://github.com/vajeen/tfdocs
Project-URL: Issues, https://github.com/vajeen/tfdocs/issues
Author-email: Vajeen Karunathilaka <vajeen@gmail.com>
License-File: LICENCE
Classifier: License :: OSI Approved :: MIT License
Classifier: Operating System :: OS Independent
Classifier: Programming Language :: Python :: 3
Requires-Python: >=3.9
Requires-Dist: gitpython>=3.1.30
Requires-Dist: rich>=12.0.0
